ifparser/__init__.py
ifparser/ifconfig.py
ifparser/re_scan.py
ifparser-0.8.1.dist-info/DESCRIPTION.rst
ifparser-0.8.1.dist-info/METADATA
ifparser-0.8.1.dist-info/RECORD
ifparser-0.8.1.dist-info/WHEEL
ifparser-0.8.1.dist-info/metadata.json
ifparser-0.8.1.dist-info/top_level.txt
