Metadata-Version: 2.0
Name: ifparser
Version: 0.8.1
Summary: Parse ifconfig output and retrieve values with goodies
Home-page: http://github.com/ssudake21/ifconfig-parser
Author: Sanket Sudake
Author-email: sanketsudake@gmail.com
License: BSD
Download-URL: http://github.com/ssudake21/ifconfig-parser
Platform: UNKNOWN
Classifier: Development Status :: 5 - Production/Stable
Classifier: License :: OSI Approved :: BSD License
Classifier: Programming Language :: Python :: 2.7
Classifier: Operating System :: POSIX :: Linux
Classifier: Topic :: Internet
Classifier: Topic :: Software Development :: Libraries :: Python Modules
Classifier: Intended Audience :: Developers
Classifier: Intended Audience :: System Administrators
Classifier: Topic :: Software Development :: Libraries
